[{"prefecture_jis_code":"06","city_jis_code":"06207","town_name_kana":"ｱｲｵｲ","town_name":"相生","zip_code":"9993222"},{"prefecture_jis_code":"06","city_jis_code":"06207","town_name_kana":"ｱｻﾋﾀﾞｲ","town_name":"朝日台","zip_code":"9993164"},{"prefecture_jis_code":"06","city_jis_code":"06207","town_name_kana":"ｱｻﾋﾏﾁ","town_name":"旭町","zip_code":"9993106"},{"prefecture_jis_code":"06","city_jis_code":"06207","town_name_kana":"ｱﾐﾀﾞﾁ","town_name":"阿弥陀地","zip_code":"9993235"},{"prefecture_jis_code":"06","city_jis_code":"06207","town_name_kana":"ｲｼｻﾞｷ","town_name":"石崎","zip_code":"9993144"},{"prefecture_jis_code":"06","city_jis_code":"06207","town_name_kana":"ｲｼｿﾞﾈ","town_name":"石曽根","zip_code":"9993244"},{"prefecture_jis_code":"06","city_jis_code":"06207","town_name_kana":"ｲｼﾄﾞｳ","town_name":"石堂","zip_code":"9993231"},{"prefecture_jis_code":"06","city_jis_code":"06207","town_name_kana":"ｲｽﾞﾐｶﾜ","town_name":"泉川","zip_code":"9993105"},{"prefecture_jis_code":"06","city_jis_code":"06207","town_name_kana":"ｳﾗﾏﾁ","town_name":"裏町","zip_code":"9993165"},{"prefecture_jis_code":"06","city_jis_code":"06207","town_name_kana":"ｵｲﾄﾞﾁｮｳ","town_name":"御井戸丁","zip_code":"9993157"},{"prefecture_jis_code":"06","city_jis_code":"06207","town_name_kana":"ｵｵｲｼ","town_name":"大石","zip_code":"9993167"},{"prefecture_jis_code":"06","city_jis_code":"06207","town_name_kana":"ｵｸﾞﾗ","town_name":"小倉","zip_code":"9993112"},{"prefecture_jis_code":"06","city_jis_code":"06207","town_name_kana":"ｵｻﾞｻ","town_name":"小笹","zip_code":"9993214"},{"prefecture_jis_code":"06","city_jis_code":"06207","town_name_kana":"ｵｼﾞﾗﾌ","town_name":"小白府","zip_code":"9993172"},{"prefecture_jis_code":"06","city_jis_code":"06207","town_name_kana":"ｶﾅｵｲ","town_name":"金生","zip_code":"9993124"},{"prefecture_jis_code":"06","city_jis_code":"06207","town_name_kana":"ｶﾅｵｲﾆｼ","town_name":"金生西","zip_code":"9993126"},{"prefecture_jis_code":"06","city_jis_code":"06207","town_name_kana":"ｶﾅｵｲﾋｶﾞｼ","town_name":"金生東","zip_code":"9993125"},{"prefecture_jis_code":"06","city_jis_code":"06207","town_name_kana":"ｶﾅｶﾒ","town_name":"金瓶","zip_code":"9993101"},{"prefecture_jis_code":"06","city_jis_code":"06207","town_name_kana":"ｶﾅﾔ","town_name":"金谷","zip_code":"9993103"},{"prefecture_jis_code":"06","city_jis_code":"06207","town_name_kana":"ｶﾈﾔﾏ","town_name":"金山","zip_code":"9993226"},{"prefecture_jis_code":"06","city_jis_code":"06207","town_name_kana":"ｶﾐﾅﾏｲ","town_name":"上生居","zip_code":"9993204"},{"prefecture_jis_code":"06","city_jis_code":"06207","town_name_kana":"ｶﾙｲｻﾞﾜ","town_name":"軽井沢","zip_code":"9993163"},{"prefecture_jis_code":"06","city_jis_code":"06207","town_name_kana":"ｶﾜｸﾞﾁ","town_name":"川口","zip_code":"9993245"},{"prefecture_jis_code":"06","city_jis_code":"06207","town_name_kana":"ｶﾜｻｷ","town_name":"河崎","zip_code":"9993145"},{"prefecture_jis_code":"06","city_jis_code":"06207","town_name_kana":"ｷﾀﾏﾁ","town_name":"北町","zip_code":"9993131"},{"prefecture_jis_code":"06","city_jis_code":"06207","town_name_kana":"ｷﾀﾏﾁﾎﾝﾁｮｳ","town_name":"北町本丁","zip_code":"9993151"},{"prefecture_jis_code":"06","city_jis_code":"06207","town_name_kana":"ｸﾎﾞｶﾜ","town_name":"久保川","zip_code":"9993215"},{"prefecture_jis_code":"06","city_jis_code":"06207","town_name_kana":"ｸﾎﾞﾃ","town_name":"久保手","zip_code":"9993166"},{"prefecture_jis_code":"06","city_jis_code":"06207","town_name_kana":"ｹﾔｷﾉﾓﾘ","town_name":"けやきの森","zip_code":"9993241"},{"prefecture_jis_code":"06","city_jis_code":"06207","town_name_kana":"ｺｱﾅ","town_name":"小穴","zip_code":"9993237"},{"prefecture_jis_code":"06","city_jis_code":"06207","town_name_kana":"ｺｳﾔ","town_name":"高野","zip_code":"9993115"},{"prefecture_jis_code":"06","city_jis_code":"06207","town_name_kana":"ｺﾞﾝｹﾞﾝﾄﾞｳ","town_name":"権現堂","zip_code":"9993111"},{"prefecture_jis_code":"06","city_jis_code":"06207","town_name_kana":"ｻｶｴﾏﾁ","town_name":"栄町","zip_code":"9993132"},{"prefecture_jis_code":"06","city_jis_code":"06207","town_name_kana":"ｻﾜﾁｮｳ","town_name":"沢丁","zip_code":"9993142"},{"prefecture_jis_code":"06","city_jis_code":"06207","town_name_kana":"ｻﾝﾎﾞﾝﾏﾂ","town_name":"三本松","zip_code":"9993233"},{"prefecture_jis_code":"06","city_jis_code":"06207","town_name_kana":"ｻﾞｵｳ","town_name":"蔵王","zip_code":"9993113"},{"prefecture_jis_code":"06","city_jis_code":"06207","town_name_kana":"ｻﾞｵｳﾉﾓﾘ","town_name":"蔵王の森","zip_code":"9993104"},{"prefecture_jis_code":"06","city_jis_code":"06207","town_name_kana":"ｼｮｳﾌﾞ","town_name":"菖蒲","zip_code":"9993217"},{"prefecture_jis_code":"06","city_jis_code":"06207","town_name_kana":"ｼﾓﾅﾏｲ","town_name":"下生居","zip_code":"9993202"},{"prefecture_jis_code":"06","city_jis_code":"06207","town_name_kana":"ｼﾝｶﾅﾔ","town_name":"新金谷","zip_code":"9993102"},{"prefecture_jis_code":"06","city_jis_code":"06207","town_name_kana":"ｼﾝﾁｮｳ","town_name":"新丁","zip_code":"9993152"},{"prefecture_jis_code":"06","city_jis_code":"06207","town_name_kana":"ｼﾝﾏﾁ","town_name":"新町","zip_code":"9993158"},{"prefecture_jis_code":"06","city_jis_code":"06207","town_name_kana":"ｼﾝﾕ","town_name":"新湯","zip_code":"9993141"},{"prefecture_jis_code":"06","city_jis_code":"06207","town_name_kana":"ｽﾀﾞｲﾀ","town_name":"須田板","zip_code":"9993213"},{"prefecture_jis_code":"06","city_jis_code":"06207","town_name_kana":"ｾｷﾈ","town_name":"関根","zip_code":"9993221"},{"prefecture_jis_code":"06","city_jis_code":"06207","town_name_kana":"ｾﾝｺﾞｸ","town_name":"仙石","zip_code":"9993122"},{"prefecture_jis_code":"06","city_jis_code":"06207","town_name_kana":"ﾀｶﾏﾂ","town_name":"高松","zip_code":"9993243"},{"prefecture_jis_code":"06","city_jis_code":"06207","town_name_kana":"ﾀﾞｲﾓﾝ","town_name":"大門","zip_code":"9993216"},{"prefecture_jis_code":"06","city_jis_code":"06207","town_name_kana":"ﾂﾙﾊｷﾞﾁｮｳ","town_name":"鶴脛町","zip_code":"9993155"},{"prefecture_jis_code":"06","city_jis_code":"06207","town_name_kana":"ﾄｳｺﾞ","town_name":"藤吾","zip_code":"9993234"},{"prefecture_jis_code":"06","city_jis_code":"06207","town_name_kana":"ﾄｵｶﾏﾁ","town_name":"十日町","zip_code":"9993153"},{"prefecture_jis_code":"06","city_jis_code":"06207","town_name_kana":"ﾅｶﾅﾏｲ","town_name":"中生居","zip_code":"9993203"},{"prefecture_jis_code":"06","city_jis_code":"06207","town_name_kana":"ﾅｶﾔﾏ","town_name":"中山","zip_code":"9993246"},{"prefecture_jis_code":"06","city_jis_code":"06207","town_name_kana":"ﾅｶﾞｼﾐｽﾞ","town_name":"長清水","zip_code":"9993232"},{"prefecture_jis_code":"06","city_jis_code":"06207","town_name_kana":"ﾅｶﾞﾉ","town_name":"永野","zip_code":"9993114"},{"prefecture_jis_code":"06","city_jis_code":"06207","town_name_kana":"ﾅﾗｹﾞ","town_name":"楢下","zip_code":"9993225"},{"prefecture_jis_code":"06","city_jis_code":"06207","town_name_kana":"ﾊﾔﾏ","town_name":"葉山","zip_code":"9993242"},{"prefecture_jis_code":"06","city_jis_code":"06207","town_name_kana":"ﾊﾗｸﾞﾁ","town_name":"原口","zip_code":"9993212"},{"prefecture_jis_code":"06","city_jis_code":"06207","town_name_kana":"ﾋｶﾞｼﾏﾁ","town_name":"東町","zip_code":"9993121"},{"prefecture_jis_code":"06","city_jis_code":"06207","town_name_kana":"ﾌﾂｶﾏﾁ","town_name":"二日町","zip_code":"9993143"},{"prefecture_jis_code":"06","city_jis_code":"06207","town_name_kana":"ﾍﾞﾝﾃﾝ","town_name":"弁天","zip_code":"9993161"},{"prefecture_jis_code":"06","city_jis_code":"06207","town_name_kana":"ﾎｿﾔ","town_name":"細谷","zip_code":"9993236"},{"prefecture_jis_code":"06","city_jis_code":"06207","town_name_kana":"ﾏｷﾞﾉ","town_name":"牧野","zip_code":"9993211"},{"prefecture_jis_code":"06","city_jis_code":"06207","town_name_kana":"ﾏﾂﾔﾏ","town_name":"松山","zip_code":"9993146"},{"prefecture_jis_code":"06","city_jis_code":"06207","town_name_kana":"ﾐｶﾐ","town_name":"三上","zip_code":"9993223"},{"prefecture_jis_code":"06","city_jis_code":"06207","town_name_kana":"ﾐｻｷﾁｮｳ","town_name":"美咲町","zip_code":"9993123"},{"prefecture_jis_code":"06","city_jis_code":"06207","town_name_kana":"ﾐﾅｻﾞﾜ","town_name":"皆沢","zip_code":"9993224"},{"prefecture_jis_code":"06","city_jis_code":"06207","town_name_kana":"ﾐﾅﾐﾏﾁ","town_name":"南町","zip_code":"9993135"},{"prefecture_jis_code":"06","city_jis_code":"06207","town_name_kana":"ﾐﾊﾗｼﾉｵｶ","town_name":"みはらしの丘","zip_code":"9993107"},{"prefecture_jis_code":"06","city_jis_code":"06207","town_name_kana":"ﾐﾔﾉﾜｷ","town_name":"宮脇","zip_code":"9993201"},{"prefecture_jis_code":"06","city_jis_code":"06207","town_name_kana":"ﾑｼﾞﾅﾓﾘ","town_name":"狸森","zip_code":"9993171"},{"prefecture_jis_code":"06","city_jis_code":"06207","town_name_kana":"ﾓﾄｼﾞｮｳﾅｲ","town_name":"元城内","zip_code":"9993154"},{"prefecture_jis_code":"06","city_jis_code":"06207","town_name_kana":"ﾔﾗｲ","town_name":"矢来","zip_code":"9993134"},{"prefecture_jis_code":"06","city_jis_code":"06207","town_name_kana":"ﾕﾏﾁ","town_name":"湯町","zip_code":"9993156"},{"prefecture_jis_code":"06","city_jis_code":"06207","town_name_kana":"ﾖｳｶﾏﾁ","town_name":"八日町","zip_code":"9993133"},{"prefecture_jis_code":"06","city_jis_code":"06207","town_name_kana":"ﾖﾂﾔ","town_name":"四ツ谷","zip_code":"9993162"}]