[{"prefecture_jis_code":"06","city_jis_code":"06323","town_name_kana":"ｵｵｸﾞﾚﾔﾏ","town_name":"大暮山"},{"prefecture_jis_code":"06","city_jis_code":"06323","town_name_kana":"ｵｵﾌﾅｷﾞ","town_name":"大船木"},{"prefecture_jis_code":"06","city_jis_code":"06323","town_name_kana":"ｵｸﾘﾊｼ","town_name":"送橋"},{"prefecture_jis_code":"06","city_jis_code":"06323","town_name_kana":"ｺｸｽﾍﾞ","town_name":"石須部"},{"prefecture_jis_code":"06","city_jis_code":"06323","town_name_kana":"ｺﾝﾍﾟｲ","town_name":"今平"},{"prefecture_jis_code":"06","city_jis_code":"06323","town_name_kana":"ｼﾉｻﾜ","town_name":"四ノ沢"},{"prefecture_jis_code":"06","city_jis_code":"06323","town_name_kana":"ﾀﾏﾉｲ","town_name":"玉ノ井"},{"prefecture_jis_code":"06","city_jis_code":"06323","town_name_kana":"ﾀﾛｳ","town_name":"太郎"},{"prefecture_jis_code":"06","city_jis_code":"06323","town_name_kana":"ﾌﾙﾏｷﾞ","town_name":"古槇"},{"prefecture_jis_code":"06","city_jis_code":"06323","town_name_kana":"ﾏﾂﾎﾄﾞ","town_name":"松程"},{"prefecture_jis_code":"06","city_jis_code":"06323","town_name_kana":"ﾐｽﾞﾓﾄ","town_name":"水本"},{"prefecture_jis_code":"06","city_jis_code":"06323","town_name_kana":"ﾐﾅｶ","town_name":"三中"},{"prefecture_jis_code":"06","city_jis_code":"06323","town_name_kana":"ﾐﾔｼﾞｭｸ","town_name":"宮宿"},{"prefecture_jis_code":"06","city_jis_code":"06323","town_name_kana":"ﾕｷﾀﾆ","town_name":"雪谷"},{"prefecture_jis_code":"06","city_jis_code":"06323","town_name_kana":"ﾜｺﾞｳﾀｲﾗ","town_name":"和合平"}]