[{"prefecture_jis_code":"11","city_jis_code":"11239","town_name_kana":"ｱｵﾀ","town_name":"粟生田"},{"prefecture_jis_code":"11","city_jis_code":"11239","town_name_kana":"ｱｶｵ","town_name":"赤尾"},{"prefecture_jis_code":"11","city_jis_code":"11239","town_name_kana":"ｱｻﾊﾞ","town_name":"浅羽"},{"prefecture_jis_code":"11","city_jis_code":"11239","town_name_kana":"ｱｻﾊﾞﾉ","town_name":"浅羽野"},{"prefecture_jis_code":"11","city_jis_code":"11239","town_name_kana":"ｱｼﾔﾏﾁｮｳ","town_name":"芦山町"},{"prefecture_jis_code":"11","city_jis_code":"11239","town_name_kana":"ｱﾂｶﾞﾜ","town_name":"厚川"},{"prefecture_jis_code":"11","city_jis_code":"11239","town_name_kana":"ｲｽﾞﾉﾔﾏﾁｮｳ","town_name":"伊豆の山町"},{"prefecture_jis_code":"11","city_jis_code":"11239","town_name_kana":"ｲﾏﾆｼ","town_name":"今西"},{"prefecture_jis_code":"11","city_jis_code":"11239","town_name_kana":"ｶｹﾉｳｴ","town_name":"欠ノ上"},{"prefecture_jis_code":"11","city_jis_code":"11239","town_name_kana":"ｶﾀﾔﾅｷﾞｼﾝﾃﾞﾝ","town_name":"片柳新田"},{"prefecture_jis_code":"11","city_jis_code":"11239","town_name_kana":"ｶﾏｸﾗﾁｮｳ","town_name":"鎌倉町"},{"prefecture_jis_code":"11","city_jis_code":"11239","town_name_kana":"ｶﾔｶﾞﾀ","town_name":"萱方"},{"prefecture_jis_code":"11","city_jis_code":"11239","town_name_kana":"ｷﾀｱｻﾊﾞ","town_name":"北浅羽"},{"prefecture_jis_code":"11","city_jis_code":"11239","town_name_kana":"ｷﾀﾐﾈ","town_name":"北峰"},{"prefecture_jis_code":"11","city_jis_code":"11239","town_name_kana":"ｼﾝｶﾞﾔ","town_name":"新ケ谷"},{"prefecture_jis_code":"11","city_jis_code":"11239","town_name_kana":"ｼﾞｮｳｶﾞﾝｼﾞ","town_name":"成願寺"},{"prefecture_jis_code":"11","city_jis_code":"11239","town_name_kana":"ｾｷﾏ","town_name":"関間"},{"prefecture_jis_code":"11","city_jis_code":"11239","town_name_kana":"ｾﾞﾝﾉｳｼﾞ","town_name":"善能寺"},{"prefecture_jis_code":"11","city_jis_code":"11239","town_name_kana":"ﾀﾜﾒ","town_name":"多和目"},{"prefecture_jis_code":"11","city_jis_code":"11239","town_name_kana":"ﾄｸﾞﾁ","town_name":"戸口"},{"prefecture_jis_code":"11","city_jis_code":"11239","town_name_kana":"ﾄﾐﾔ","town_name":"戸宮"},{"prefecture_jis_code":"11","city_jis_code":"11239","town_name_kana":"ﾅｶｵｻｶ","town_name":"中小坂"},{"prefecture_jis_code":"11","city_jis_code":"11239","town_name_kana":"ﾆｯｻｲﾊﾅﾐｽﾞｷ","town_name":"にっさい花みず木"},{"prefecture_jis_code":"11","city_jis_code":"11239","town_name_kana":"ﾆｼｲﾝﾀｰ","town_name":"西インター"},{"prefecture_jis_code":"11","city_jis_code":"11239","town_name_kana":"ﾆｼｻｶﾄﾞ","town_name":"西坂戸"},{"prefecture_jis_code":"11","city_jis_code":"11239","town_name_kana":"ﾊﾅｶｹﾞﾁｮｳ","town_name":"花影町"},{"prefecture_jis_code":"11","city_jis_code":"11239","town_name_kana":"ﾋｶﾞｼｻｶﾄﾞ","town_name":"東坂戸"},{"prefecture_jis_code":"11","city_jis_code":"11239","town_name_kana":"ﾐｿﾞﾊﾀﾁｮｳ","town_name":"溝端町"},{"prefecture_jis_code":"11","city_jis_code":"11239","town_name_kana":"ﾖｯｶｲﾁﾊﾞ","town_name":"四日市場"},{"prefecture_jis_code":"11","city_jis_code":"11239","town_name_kana":"ﾖｺﾇﾏ","town_name":"横沼"}]