[{"prefecture_jis_code":"04","city_jis_code":"04301","zip_code":"9890921","prefecture_name_kana":"ﾐﾔｷﾞｹﾝ","city_name_kana":"ｶｯﾀｸﾞﾝｻﾞｵｳﾏﾁ","town_name_kana":"ｴﾝﾀﾞ","prefecture_name":"宮城県","city_name":"刈田郡蔵王町","town_name":"円田"},{"prefecture_jis_code":"04","city_jis_code":"04301","zip_code":"9890921","prefecture_name_kana":"ﾐﾔｷﾞｹﾝ","city_name_kana":"ｶｯﾀｸﾞﾝｻﾞｵｳﾏﾁ","town_name_kana":"ｴﾝﾀﾞｶﾏｻﾞﾜ","prefecture_name":"宮城県","city_name":"刈田郡蔵王町","town_name":"円田釜沢"},{"prefecture_jis_code":"04","city_jis_code":"04301","zip_code":"9890921","prefecture_name_kana":"ﾐﾔｷﾞｹﾝ","city_name_kana":"ｶｯﾀｸﾞﾝｻﾞｵｳﾏﾁ","town_name_kana":"ｴﾝﾀﾞｾﾞﾝﾌﾞﾓﾘ","prefecture_name":"宮城県","city_name":"刈田郡蔵王町","town_name":"円田善舞森"},{"prefecture_jis_code":"04","city_jis_code":"04301","zip_code":"9890921","prefecture_name_kana":"ﾐﾔｷﾞｹﾝ","city_name_kana":"ｶｯﾀｸﾞﾝｻﾞｵｳﾏﾁ","town_name_kana":"ｴﾝﾀﾞﾄﾞﾌﾞﾔﾁ","prefecture_name":"宮城県","city_name":"刈田郡蔵王町","town_name":"円田土浮谷地"}]