[{"prefecture_jis_code":"34","city_jis_code":"34309","town_name_kana":"ｳｴﾀﾞ","town_name":"植田","zip_code":"7314321"},{"prefecture_jis_code":"34","city_jis_code":"34309","town_name_kana":"ｷﾀｼﾝﾁ","town_name":"北新地","zip_code":"7314311"},{"prefecture_jis_code":"34","city_jis_code":"34309","town_name_kana":"ｺﾔｳﾗ","town_name":"小屋浦","zip_code":"7314331"},{"prefecture_jis_code":"34","city_jis_code":"34309","town_name_kana":"ｻｶﾆｼ","town_name":"坂西","zip_code":"7314314"},{"prefecture_jis_code":"34","city_jis_code":"34309","town_name_kana":"ｻｶﾋｶﾞｼ","town_name":"坂東","zip_code":"7314313"},{"prefecture_jis_code":"34","city_jis_code":"34309","town_name_kana":"ﾀｲﾋﾞ","town_name":"鯛尾","zip_code":"7314325"},{"prefecture_jis_code":"34","city_jis_code":"34309","town_name_kana":"ﾍｲｾｲｶﾞﾊﾏ","town_name":"平成ケ浜","zip_code":"7314312"},{"prefecture_jis_code":"34","city_jis_code":"34309","town_name_kana":"ﾖｺﾊﾏﾁｭｳｵｳ","town_name":"横浜中央","zip_code":"7314323"},{"prefecture_jis_code":"34","city_jis_code":"34309","town_name_kana":"ﾖｺﾊﾏﾆｼ","town_name":"横浜西","zip_code":"7314324"},{"prefecture_jis_code":"34","city_jis_code":"34309","town_name_kana":"ﾖｺﾊﾏﾋｶﾞｼ","town_name":"横浜東","zip_code":"7314322"}]