[{"prefecture_jis_code":"29","city_jis_code":"29322","town_name_kana":"ｵｿｾ","town_name":"遅瀬"},{"prefecture_jis_code":"29","city_jis_code":"29322","town_name_kana":"ｶﾂﾊﾗ","town_name":"勝原"},{"prefecture_jis_code":"29","city_jis_code":"29322","town_name_kana":"ｷﾘﾊﾀ","town_name":"切幡"},{"prefecture_jis_code":"29","city_jis_code":"29322","town_name_kana":"ｹﾊﾗ","town_name":"毛原"},{"prefecture_jis_code":"29","city_jis_code":"29322","town_name_kana":"ｾﾞﾐｮｳ","town_name":"助命"},{"prefecture_jis_code":"29","city_jis_code":"29322","town_name_kana":"ﾁｭｳﾑｻﾞﾝ","town_name":"中峰山"},{"prefecture_jis_code":"29","city_jis_code":"29322","town_name_kana":"ﾄﾞｳﾏｴ","town_name":"堂前"},{"prefecture_jis_code":"29","city_jis_code":"29322","town_name_kana":"ﾅｶﾉｼｮｳ","town_name":"中之庄"},{"prefecture_jis_code":"29","city_jis_code":"29322","town_name_kana":"ﾆｼﾊﾀ","town_name":"西波多"},{"prefecture_jis_code":"29","city_jis_code":"29322","town_name_kana":"ﾋﾛﾀﾞｲ","town_name":"広代"},{"prefecture_jis_code":"29","city_jis_code":"29322","town_name_kana":"ﾌｼｵｶﾞﾐ","town_name":"伏拝"},{"prefecture_jis_code":"29","city_jis_code":"29322","town_name_kana":"ﾏﾄﾉ","town_name":"的野"},{"prefecture_jis_code":"29","city_jis_code":"29322","town_name_kana":"ﾐﾈﾃﾞﾗ","town_name":"峰寺"},{"prefecture_jis_code":"29","city_jis_code":"29322","town_name_kana":"ﾑﾛﾂﾞ","town_name":"室津"}]